mbonig/secure_bucket/__init__.py
mbonig/secure_bucket/py.typed
mbonig/secure_bucket/_jsii/__init__.py
mbonig/secure_bucket/_jsii/secure-bucket@1.0.8.jsii.tgz
mbonig.secure_bucket-1.0.8.dist-info/METADATA
mbonig.secure_bucket-1.0.8.dist-info/WHEEL
mbonig.secure_bucket-1.0.8.dist-info/top_level.txt
mbonig.secure_bucket-1.0.8.dist-info/RECORD
