Metadata-Version: 2.1
Name: mbonig.secure-bucket
Version: 1.0.8
Summary: An AWS CDK Construct that enforces encryption on an S3 bucket
Home-page: https://github.com/mbonig/secure-bucket.git
Author: Matthew Bonig<matthew.bonig@gmail.com>
License: MIT
Project-URL: Source, https://github.com/mbonig/secure-bucket.git
Platform: UNKNOWN
Classifier: Intended Audience :: Developers
Classifier: Operating System :: OS Independent
Classifier: Programming Language :: JavaScript
Classifier: Programming Language :: Python :: 3 :: Only
Classifier: Programming Language :: Python :: 3.6
Classifier: Programming Language :: Python :: 3.7
Classifier: Programming Language :: Python :: 3.8
Classifier: Typing :: Typed
Classifier: License :: OSI Approved
Requires-Python: >=3.6
Requires-Dist: jsii (~=0.21.2)
Requires-Dist: publication (>=0.0.3)
Requires-Dist: aws-cdk.aws-s3 (<2.0.0,>=1.22.0)
Requires-Dist: aws-cdk.core (<2.0.0,>=1.22.0)
